maintenance/__init__.py
maintenance.py-0.2.0.dist-info/LICENSE
maintenance.py-0.2.0.dist-info/METADATA
maintenance.py-0.2.0.dist-info/WHEEL
maintenance.py-0.2.0.dist-info/top_level.txt
maintenance.py-0.2.0.dist-info/RECORD
