Metadata-Version: 2.1
Name: maintenance.py
Version: 0.2.0
Summary: Utilities for Maintenance
Author: Jonas da Silva
License: MIT
Project-URL: Source Code, https://github.com/phoenixr-codes/maintenance.py
Keywords: deprecate,todo
Classifier: Development Status :: 5 - Production/Stable
Classifier: License :: OSI Approved :: MIT License
Classifier: Natural Language :: English
Classifier: Programming Language :: Python :: 3
Classifier: Topic :: Documentation :: Sphinx
Classifier: Topic :: Software Development :: Documentation
Classifier: Topic :: Utilities
Classifier: Typing :: Typed
Requires-Python: >=3.10
License-File: LICENSE
